{"nodes": [{"id": "g_my_projects_aagriggate_backend_src_main_java_com_mywebpage_register_login_auth_dto_authresponsedto_java", "label": "AuthResponseDTO.java", "file_type": "code", "source_file": "G:\\MY_PROJECTS\\AagriGgate\\backend\\src\\main\\java\\com\\MyWebpage\\register\\login\\auth\\dto\\AuthResponseDTO.java", "source_location": "L1"}, {"id": "authresponsedto_authresponsedto", "label": "AuthResponseDTO", "file_type": "code", "source_file": "G:\\MY_PROJECTS\\AagriGgate\\backend\\src\\main\\java\\com\\MyWebpage\\register\\login\\auth\\dto\\AuthResponseDTO.java", "source_location": "L3"}, {"id": "authresponsedto_authresponsedto_authresponsedto", "label": ".AuthResponseDTO()", "file_type": "code", "source_file": "G:\\MY_PROJECTS\\AagriGgate\\backend\\src\\main\\java\\com\\MyWebpage\\register\\login\\auth\\dto\\AuthResponseDTO.java", "source_location": "L8"}, {"id": "authresponsedto_authresponsedto_gettoken", "label": ".getToken()", "file_type": "code", "source_file": "G:\\MY_PROJECTS\\AagriGgate\\backend\\src\\main\\java\\com\\MyWebpage\\register\\login\\auth\\dto\\AuthResponseDTO.java", "source_location": "L22"}, {"id": "authresponsedto_authresponsedto_settoken", "label": ".setToken()", "file_type": "code", "source_file": "G:\\MY_PROJECTS\\AagriGgate\\backend\\src\\main\\java\\com\\MyWebpage\\register\\login\\auth\\dto\\AuthResponseDTO.java", "source_location": "L23"}, {"id": "authresponsedto_authresponsedto_getrole", "label": ".getRole()", "file_type": "code", "source_file": "G:\\MY_PROJECTS\\AagriGgate\\backend\\src\\main\\java\\com\\MyWebpage\\register\\login\\auth\\dto\\AuthResponseDTO.java", "source_location": "L24"}, {"id": "authresponsedto_authresponsedto_setrole", "label": ".setRole()", "file_type": "code", "source_file": "G:\\MY_PROJECTS\\AagriGgate\\backend\\src\\main\\java\\com\\MyWebpage\\register\\login\\auth\\dto\\AuthResponseDTO.java", "source_location": "L25"}, {"id": "authresponsedto_authresponsedto_getfarmerid", "label": ".getFarmerId()", "file_type": "code", "source_file": "G:\\MY_PROJECTS\\AagriGgate\\backend\\src\\main\\java\\com\\MyWebpage\\register\\login\\auth\\dto\\AuthResponseDTO.java", "source_location": "L26"}, {"id": "authresponsedto_authresponsedto_setfarmerid", "label": ".setFarmerId()", "file_type": "code", "source_file": "G:\\MY_PROJECTS\\AagriGgate\\backend\\src\\main\\java\\com\\MyWebpage\\register\\login\\auth\\dto\\AuthResponseDTO.java", "source_location": "L27"}], "edges": [{"source": "g_my_projects_aagriggate_backend_src_main_java_com_mywebpage_register_login_auth_dto_authresponsedto_java", "target": "authresponsedto_authresponsedto", "relation": "contains", "confidence": "EXTRACTED", "source_file": "G:\\MY_PROJECTS\\AagriGgate\\backend\\src\\main\\java\\com\\MyWebpage\\register\\login\\auth\\dto\\AuthResponseDTO.java", "source_location": "L3", "weight": 1.0}, {"source": "authresponsedto_authresponsedto", "target": "authresponsedto_authresponsedto_authresponsedto", "relation": "method", "confidence": "EXTRACTED", "source_file": "G:\\MY_PROJECTS\\AagriGgate\\backend\\src\\main\\java\\com\\MyWebpage\\register\\login\\auth\\dto\\AuthResponseDTO.java", "source_location": "L8", "weight": 1.0}, {"source": "authresponsedto_authresponsedto", "target": "authresponsedto_authresponsedto_authresponsedto", "relation": "method", "confidence": "EXTRACTED", "source_file": "G:\\MY_PROJECTS\\AagriGgate\\backend\\src\\main\\java\\com\\MyWebpage\\register\\login\\auth\\dto\\AuthResponseDTO.java", "source_location": "L11", "weight": 1.0}, {"source": "authresponsedto_authresponsedto", "target": "authresponsedto_authresponsedto_authresponsedto", "relation": "method", "confidence": "EXTRACTED", "source_file": "G:\\MY_PROJECTS\\AagriGgate\\backend\\src\\main\\java\\com\\MyWebpage\\register\\login\\auth\\dto\\AuthResponseDTO.java", "source_location": "L16", "weight": 1.0}, {"source": "authresponsedto_authresponsedto", "target": "authresponsedto_authresponsedto_gettoken", "relation": "method", "confidence": "EXTRACTED", "source_file": "G:\\MY_PROJECTS\\AagriGgate\\backend\\src\\main\\java\\com\\MyWebpage\\register\\login\\auth\\dto\\AuthResponseDTO.java", "source_location": "L22", "weight": 1.0}, {"source": "authresponsedto_authresponsedto", "target": "authresponsedto_authresponsedto_settoken", "relation": "method", "confidence": "EXTRACTED", "source_file": "G:\\MY_PROJECTS\\AagriGgate\\backend\\src\\main\\java\\com\\MyWebpage\\register\\login\\auth\\dto\\AuthResponseDTO.java", "source_location": "L23", "weight": 1.0}, {"source": "authresponsedto_authresponsedto", "target": "authresponsedto_authresponsedto_getrole", "relation": "method", "confidence": "EXTRACTED", "source_file": "G:\\MY_PROJECTS\\AagriGgate\\backend\\src\\main\\java\\com\\MyWebpage\\register\\login\\auth\\dto\\AuthResponseDTO.java", "source_location": "L24", "weight": 1.0}, {"source": "authresponsedto_authresponsedto", "target": "authresponsedto_authresponsedto_setrole", "relation": "method", "confidence": "EXTRACTED", "source_file": "G:\\MY_PROJECTS\\AagriGgate\\backend\\src\\main\\java\\com\\MyWebpage\\register\\login\\auth\\dto\\AuthResponseDTO.java", "source_location": "L25", "weight": 1.0}, {"source": "authresponsedto_authresponsedto", "target": "authresponsedto_authresponsedto_getfarmerid", "relation": "method", "confidence": "EXTRACTED", "source_file": "G:\\MY_PROJECTS\\AagriGgate\\backend\\src\\main\\java\\com\\MyWebpage\\register\\login\\auth\\dto\\AuthResponseDTO.java", "source_location": "L26", "weight": 1.0}, {"source": "authresponsedto_authresponsedto", "target": "authresponsedto_authresponsedto_setfarmerid", "relation": "method", "confidence": "EXTRACTED", "source_file": "G:\\MY_PROJECTS\\AagriGgate\\backend\\src\\main\\java\\com\\MyWebpage\\register\\login\\auth\\dto\\AuthResponseDTO.java", "source_location": "L27", "weight": 1.0}], "raw_calls": []}